solcast_pv/__init__.py
solcast_pv/exceptions.py
solcast_pv/models.py
solcast_pv/py.typed
solcast_pv/solcast_pv.py
solcast_pv-0.1.0.dist-info/LICENSE
solcast_pv-0.1.0.dist-info/METADATA
solcast_pv-0.1.0.dist-info/WHEEL
solcast_pv-0.1.0.dist-info/RECORD
