Metadata-Version: 2.1
Name: solcast-pv
Version: 0.1.0
Summary: Asynchronous Python client for getting forecast data from Solcast
Home-page: https://github.com/klaasnicolaas/python-solcast-pv
License: MIT
Keywords: api,async,client,solcast,forecast,energy,solar
Author: Klaas Schoute
Author-email: hello@student-techlife.com
Maintainer: Klaas Schoute
Maintainer-email: hello@student-techlife.com
Requires-Python: >=3.11,<4.0
Classifier: Framework :: AsyncIO
Classifier: Intended Audience :: Developers
Classifier: License :: OSI Approved :: MIT License
Classifier: Natural Language :: English
Classifier: Programming Language :: Python :: 3
Classifier: Programming Language :: Python :: 3.11
Classifier: Programming Language :: Python :: 3.12
Classifier: Topic :: Software Development :: Libraries :: Python Modules
Requires-Dist: aiohttp (>=3.0.0)
Requires-Dist: yarl (>=1.6.0)
Project-URL: Bug Tracker, https://github.com/klaasnicolaas/python-solcast-pv/issues
Project-URL: Changelog, https://github.com/klaasnicolaas/python-solcast-pv/releases
Project-URL: Documentation, https://github.com/klaasnicolaas/python-solcast-pv
Project-URL: Repository, https://github.com/klaasnicolaas/python-solcast-pv
